gtfs_tripify/__init__.py
gtfs_tripify/ops.py
gtfs_tripify/tripify.py
gtfs_tripify/utils.py
gtfs_tripify-0.0.3.dist-info/METADATA
gtfs_tripify-0.0.3.dist-info/WHEEL
gtfs_tripify-0.0.3.dist-info/top_level.txt
gtfs_tripify-0.0.3.dist-info/RECORD
