Metadata-Version: 2.1
Name: gtfs-tripify
Version: 0.0.3
Summary: TODO.
Home-page: https://github.com/ResidentMario/gtfs-tripify
Author: Aleksey Bilogur
Author-email: aleksey.bilogur@gmail.com
License: UNKNOWN
Download-URL: https://github.com/ResidentMario/gtfs-tripify/tarball/0.0.1
Keywords: TODO
Platform: UNKNOWN
Requires-Dist: numpy
Requires-Dist: pandas
Requires-Dist: requests
Requires-Dist: gtfs-realtime-bindings
Provides-Extra: tests
Requires-Dist: pytest ; extra == 'tests'
